markplates/__init__.py
markplates/__main__.py
markplates-1.7.0.dist-info/LICENSE
markplates-1.7.0.dist-info/METADATA
markplates-1.7.0.dist-info/WHEEL
markplates-1.7.0.dist-info/entry_points.txt
markplates-1.7.0.dist-info/top_level.txt
markplates-1.7.0.dist-info/RECORD
