Metadata-Version: 2.1
Name: markplates
Version: 1.7.0
Summary: Inject code snippets into your Markdown docs
Home-page: https://github.com/jima80525/markplates
Author: Jim Anderson
Author-email: jima.coding@gmail.com
License: MIT
Platform: UNKNOWN
Classifier: License :: OSI Approved :: MIT License
Classifier: Programming Language :: Python
Classifier: Programming Language :: Python :: 3
Classifier: Programming Language :: Python :: 3.7
Requires-Python: >=3.6.0
Requires-Dist: asttokens (==2.0.4)
Requires-Dist: Click (==7.1.2)
Requires-Dist: Jinja2 (==2.11.2)
Requires-Dist: pyperclip (==1.8.0)
